ldapsearchad/__init__.py
ldapsearchad/colors.py
ldapsearchad/example.py
ldapsearchad/exceptions.py
ldapsearchad/ldapsearchad.py
ldapsearchad/logging.py
ldapsearchad/utils.py
ldapsearchad-2024.12.10.data/scripts/ldapsearch-ad.py
ldapsearchad-2024.12.10.dist-info/LICENSE
ldapsearchad-2024.12.10.dist-info/METADATA
ldapsearchad-2024.12.10.dist-info/WHEEL
ldapsearchad-2024.12.10.dist-info/top_level.txt
ldapsearchad-2024.12.10.dist-info/RECORD
