Metadata-Version: 2.1
Name: ldapsearchad
Version: 2024.12.10
Summary: ldapsearch tool to find vulnerable configuration in Active Directory
Home-page: https://github.com/yaap7ldapsearch-ad
Author-email: yaap <gracieux.guillaume@gmail.com>
License:                     GNU GENERAL PUBLIC LICENSE
Project-URL: Homepage, https://github.com/yaap7/ldapsearch-ad
Project-URL: Documentation, https://github.com/yaap7/ldapsearch-ad/blob/master/USAGE.md
Project-URL: Repository, https://github.com/yaap7/ldapsearch-ad
Project-URL: Changelog, https://github.com/yaap7/ldapsearch-ad/releases
Keywords: ldapsearch,Active Directory,pentest
Classifier: Development Status :: 5 - Production/Stable
Classifier: License :: OSI Approved :: GNU General Public License v3 (GPLv3)
Classifier: Environment :: Console
Classifier: Operating System :: POSIX
Classifier: Intended Audience :: System Administrators
Classifier: Programming Language :: Python :: 3.6
Classifier: Topic :: Security
Classifier: Topic :: System :: Systems Administration :: Authentication/Directory :: LDAP
Requires-Python: >=3.6
License-File: LICENSE
Requires-Dist: ldap3
Requires-Dist: pycryptodome
Provides-Extra: dev
Requires-Dist: black; extra == "dev"
Requires-Dist: flake8; extra == "dev"
Requires-Dist: pre-commit; extra == "dev"
Requires-Dist: bumpver; extra == "dev"
